faceangle/__init__.py
faceangle/math.py
faceangle/model.py
faceangle/models/.gitignore
faceangle/notebook.py
faceangle/pca.py
faceangle/preprocessing.py
faceangle/visualization.py
faceangle-0.3.2.dist-info/METADATA
faceangle-0.3.2.dist-info/WHEEL
faceangle-0.3.2.dist-info/RECORD
